README.txt
setup.cfg
setup.py
p2v/__init__.py
p2v/convert_p2v.py
p2v/p2v_physical_host.py
p2v/p2v_xen_host.py
p2v/sshtools.py
p2v.egg-info/PKG-INFO
p2v.egg-info/SOURCES.txt
p2v.egg-info/dependency_links.txt
p2v.egg-info/entry_points.txt
p2v.egg-info/top_level.txt
p2v.egg-info/zip-safe