Metadata-Version: 1.0
Name: p2v
Version: 2.2.7
Summary: Physical To Virtual
Home-page: https://github.com/kirbs/P2V
Author: KOVAC Arnaud
Author-email: arnaud.kovac@gmail.com
License: GNU
Keywords: p2v xen
Platform: UNKNOWN
